setup.py
a1labs/__init__.py
a1labs.egg-info/PKG-INFO
a1labs.egg-info/SOURCES.txt
a1labs.egg-info/dependency_links.txt
a1labs.egg-info/top_level.txt