Metadata-Version: 2.1
Name: a1labs
Version: 0.0.1
Summary: a1labs
Home-page: UNKNOWN
Author: Anish Agrawal
Author-email: your.email@example.com
License: UNKNOWN
Platform: UNKNOWN
